Workbook

Sheet Read Me
A1: HotelERP - QA status, module by module
A2: Complete menu and submenu coverage, findings, fixes, and the go-live sequence. Every figure is either a formula or traceable to a file in the repository.
A5: WHAT WAS DONE
A6: Scope | B6: All 60 pages (3 menus + 57 submenus) across 5 modules, all 5 roles, 6 backend services and the SPA.
A7: Live testing | B7: ~2,860 API calls against the staging deployment: 1,728 reads (144 endpoints x 5 roles x 2 surfaces) and 1,010 write probes (159 paths x 5 roles).
A8: Live page sweep | B8: 60/60 routes rendered with live data. 0 console errors, 0 failed requests, 0 broken images, 0 layout overflow.
A9: Regression | B9: 37 suites, 1,268 pytest assertions plus 73 checks in the 4 script suites, 0 failures. Identical results under ROUTE_POLICY_MODE=audit (the shipped default) and enforce.
A10: Lint | B10: ESLint: 0 errors, 10 warnings (unchanged baseline).
A12: HOW TO READ THE STATUS COLUMNS
A13: Done / Fixed in source | B13: A defect was found against this module, the fix is in the working tree, and a test that fails without the fix now passes. NOT yet on the deployment.
A14: Needs deploy | B14: The fix is in the working tree but ships disabled or unactivated. Still live as a finding until it is deployed.
A15: No defect found | B15: Tested, and nothing came up. This is NOT the same claim as 'verified perfect' - it means no test detected a problem, not that none exists.
A16: Open | B16: A real defect that is still present. No fix, or a fix that cannot be made in source.
A17: Owner decision | B17: Deliberately not changed here. The right answer depends on the business, not on the code.
A19: THE ONE THING TO KNOW BEFORE TRUSTING IT
A20: Not deployed | B20: The fixes are in the working tree. Nothing is committed or pushed. Every fix is proven by unit tests and by regenerating the permission map byte-identically - NOT by a request against the running system. Step 11 of Go-Live closes that gap.
A22: KNOWN LIMITS OF THIS AUDIT
A23: Frontend build | B23: npm run build could not run on the QA machine (@oxc-resolver's win32 binding fails ERR_DLOPEN_FAILED). Frontend changes are verified by ESLint and by Node-level HTTP tests only.
A24: Scope of destructive testing | B24: No DoS, no real payments, emails or SMS, no deletion of business records, no database resets. Write probes used record id 999999999, which cannot exist.
A25: One process defect | B25: An early probe of this audit issued DELETE against real ids expecting a 403. It was not refused, and two rows were deleted (a tax, and Room 601's photos). Both were restored. Recorded in QA/live/FINDINGS.md rather than quietly fixed.
A26: Passwords | B26: No credential appears anywhere in this workbook or in the repository's working tree. The value is supplied at seed time via SEED_PASSWORD.

Sheet Module Status
A1: Module status - done, pending, and what is still open
A2: One row per module. Page and finding counts are formulas over the 'Menu & Submenu Status' and 'Findings' tabs.
A4: Module | B4: Owning service | C4: Pages | D4: Routes | E4: Test suites | F4: Checks | G4: Findings | H4: Status
A5: Hotel / Reservations | B5: HotelServices :9005 | C5: =COUNTIF('Menu & Submenu Status'!$E$5:$E$64,"*"&A5&"*") | D5: =SUMPRODUCT(--ISNUMBER(SEARCH(A5,'Menu & Submenu Status'!$E$5:$E$64)),'Menu & Submenu Status'!$H$5:$H$64) | E5: =COUNTIF($A$16:$A$52,A5) | F5: =SUMIF($A$16:$A$52,A5,$C$16:$C$52) | G5: QA-BIZ-001 Fixed in source; QA-BIZ-002 Fixed in source; QA-SEC-006 Owner decision; QA-SEC-009 Open (module-wide) | H5: Needs deploy
A6: Master Data | B6: MasterDataServices :9015 | C6: =COUNTIF('Menu & Submenu Status'!$E$5:$E$64,"*"&A6&"*") | D6: =SUMPRODUCT(--ISNUMBER(SEARCH(A6,'Menu & Submenu Status'!$E$5:$E$64)),'Menu & Submenu Status'!$H$5:$H$64) | E6: =COUNTIF($A$16:$A$52,A6) | F6: =SUMIF($A$16:$A$52,A6,$C$16:$C$52) | G6: QA-SEC-002 Fixed in source (module-wide); QA-SEC-007 Fixed in source (module-wide) | H6: Fixed in source
A7: Restaurant (F&B) | B7: RestaurantServices :9030 | C7: =COUNTIF('Menu & Submenu Status'!$E$5:$E$64,"*"&A7&"*") | D7: =SUMPRODUCT(--ISNUMBER(SEARCH(A7,'Menu & Submenu Status'!$E$5:$E$64)),'Menu & Submenu Status'!$H$5:$H$64) | E7: =COUNTIF($A$16:$A$52,A7) | F7: =SUMIF($A$16:$A$52,A7,$C$16:$C$52) | G7: QA-SEC-002 Fixed in source (module-wide); QA-BIZ-003 Pass | H7: Fixed in source
A8: Bar | B8: BarServices :9025 | C8: =COUNTIF('Menu & Submenu Status'!$E$5:$E$64,"*"&A8&"*") | D8: =SUMPRODUCT(--ISNUMBER(SEARCH(A8,'Menu & Submenu Status'!$E$5:$E$64)),'Menu & Submenu Status'!$H$5:$H$64) | E8: =COUNTIF($A$16:$A$52,A8) | F8: =SUMIF($A$16:$A$52,A8,$C$16:$C$52) | G8: QA-SEC-002 Fixed in source (module-wide); QA-BIZ-003 Pass | H8: Fixed in source
A9: HRM / Users | B9: UserServices :9020 | C9: =COUNTIF('Menu & Submenu Status'!$E$5:$E$64,"*"&A9&"*") | D9: =SUMPRODUCT(--ISNUMBER(SEARCH(A9,'Menu & Submenu Status'!$E$5:$E$64)),'Menu & Submenu Status'!$H$5:$H$64) | E9: =COUNTIF($A$16:$A$52,A9) | F9: =SUMIF($A$16:$A$52,A9,$C$16:$C$52) | G9: QA-SEC-001 Fixed in source (module-wide); QA-DATA-001 Open | H9: Open
A10: Cross-module (SPA) | B10: Frontend SPA (aggregates every service) | C10: =COUNTIF('Menu & Submenu Status'!$E$5:$E$64,"*"&A10&"*") | D10: =SUMPRODUCT(--ISNUMBER(SEARCH(A10,'Menu & Submenu Status'!$E$5:$E$64)),'Menu & Submenu Status'!$H$5:$H$64) | E10: =COUNTIF($A$16:$A$52,A10) | F10: =SUMIF($A$16:$A$52,A10,$C$16:$C$52) | G10: QA-SEC-005 Fixed in source; QA-UX-002 Fixed in source | H10: Fixed in source
A11: Cross-cutting (build & deploy) | B11: repo root / deployment host | C11: =COUNTIF('Menu & Submenu Status'!$E$5:$E$64,"*"&A11&"*") | D11: =SUMPRODUCT(--ISNUMBER(SEARCH(A11,'Menu & Submenu Status'!$E$5:$E$64)),'Menu & Submenu Status'!$H$5:$H$64) | E11: =COUNTIF($A$16:$A$52,A11) | F11: =SUMIF($A$16:$A$52,A11,$C$16:$C$52) | G11: QA-SEC-004 Open (module-wide); QA-SEC-001b Needs deploy (module-wide); QA-SEC-008 Partial (module-wide); QA-UX-003 Fixed in source (module-wide) | H11: Needs deploy
A12: TOTAL | C12: =SUM(C5:C11) | D12: =SUM(D5:D11) | E12: =SUM(E5:E11) | F12: =SUM(F5:F11)
A14: Test suites by module
A15: Module | B15: Suite | C15: Checks
A16: Hotel / Reservations | B16: test_night_audit.py | C16: 50
A17: Hotel / Reservations | B17: test_reservation_rules.py | C17: 111
A18: Hotel / Reservations | B18: test_reservation_pricing.py | C18: 10
A19: Hotel / Reservations | B19: test_booking_validation.py | C19: 24
A20: Hotel / Reservations | B20: test_reservation_housekeeping.py | C20: 23
A21: Hotel / Reservations | B21: test_master_client.py | C21: 45
A22: Hotel / Reservations | B22: test_upload_content.py | C22: 78
A23: Hotel / Reservations | B23: test_phone_validation.py | C23: 120
A24: Hotel / Reservations | B24: test_phone_pattern_guard.py | C24: 2
A25: Hotel / Reservations | B25: test_jwt_auth.py | C25: 10
A26: Master Data | B26: test_snapshot_contract.py | C26: 12
A27: Master Data | B27: test_upload_content.py | C27: 65
... A52: Cross-cutting (build & deploy) | B52: remove_frozen_dates.py | C52: 6

Sheet Menu & Submenu Status
A1: Every menu and submenu, with its status
A2: All 60 pages from the shipped database. V/A/E/D are what each role is granted on that page. 'Reachable' is a formula over those five columns. 'Owning module' is which menu the screen sits under; 'Served by' is which services answer for it - two different questions, and the first attempt conflated them.
A4: # | B4: Kind | C4: Parent menu | D4: Label | E4: Owning module | F4: Path | G4: Served by | H4: Routes | I4: Roles | J4: Admin | K4: F.O. Manager | L4: Front Desk | M4: Housekeeping | N4: F&B | O4: Reachable | P4: QA status | Q4: Note
A5: 1 | B5: Menu | C5: - | D5: Dashboard | E5: Cross-module (SPA) | F5: /dashboard | G5: Bar, Hotel / Reservations, Master Data, Restaurant (F&B) | H5: 19 | I5: 5 | J5: V/C/E/D | K5: V | L5: V | M5: V | N5: V | O5: =COUNTIF(J5:N5,"<>-") | P5: Fixed in source | Q5: QA-SEC-005 fixed: no longer reads guest PII from user_activity_log.
A6: 2 | B6: Menu | C6: - | D6: Reservation | E6: Hotel / Reservations | F6: /reservation | G6: Hotel / Reservations, Master Data | H6: 22 | I6: 4 | J6: V/C/E/D | K6: V/C/E/D | L6: V/C/E | M6: V | N6: - | O6: =COUNTIF(J6:N6,"<>-") | P6: Needs deploy | Q6: Parent screen; 4 children.
A7: 3 | B7: Submenu | C7: Reservation | D7: Add New Reservation | E7: Hotel / Reservations | F7: /add_new_reservation | G7: Hotel / Reservations, Master Data | H7: 14 | I7: 4 | J7: V/C/E/D | K7: V/C/E/D | L7: V/C/E | M7: V | N7: - | O7: =COUNTIF(J7:N7,"<>-") | P7: Needs deploy | Q7: QA-BIZ-002 fixed: quote refuses unsellable rooms.
A8: 4 | B8: Submenu | C8: Reservation | D8: Booking | E8: Hotel / Reservations | F8: /booking | G8: Hotel / Reservations, Master Data | H8: 7 | I8: 4 | J8: V/C/E/D | K8: V/C/E/D | L8: V/C/E | M8: V | N8: - | O8: =COUNTIF(J8:N8,"<>-") | P8: Needs deploy | Q8: QA-SEC-006: Housekeeping granted view here.
A9: 5 | B9: Submenu | C9: Reservation | D9: Room View | E9: Hotel / Reservations | F9: /room_view | G9: Master Data | H9: 3 | I9: 4 | J9: V/C/E/D | K9: V/C/E/D | L9: V/C/E | M9: V | N9: - | O9: =COUNTIF(J9:N9,"<>-") | P9: Needs deploy
A10: 6 | B10: Submenu | C10: Reservation | D10: Reservation View | E10: Hotel / Reservations | F10: /reservation_view | G10: Hotel / Reservations, Master Data | H10: 2 | I10: 4 | J10: V/C/E/D | K10: V/C/E/D | L10: V/C/E | M10: V | N10: - | O10: =COUNTIF(J10:N10,"<>-") | P10: Needs deploy | Q10: QA-BIZ-001 fixed: repeat cancel is a 409.
A11: 7 | B11: Submenu | C11: Night Audit | D11: Night Audit | E11: Hotel / Reservations | F11: /night_audit | G11: Hotel / Reservations, Master Data | H11: 5 | I11: 2 | J11: V/C/E/D | K11: V/C/E | L11: - | M11: - | N11: - | O11: =COUNTIF(J11:N11,"<>-") | P11: Needs deploy | Q11: QA-SEC-009: business_date comes from the host clock.
A12: 8 | B12: Submenu | C12: Night Audit | D12: User Reserved Details | E12: Hotel / Reservations | F12: /user_reserved_details | G12: Hotel / Reservations, Master Data | H12: 3 | I12: 2 | J12: V/C/E/D | K12: V/C/E | L12: - | M12: - | N12: - | O12: =COUNTIF(J12:N12,"<>-") | P12: Needs deploy
A13: 9 | B13: Submenu | C13: Night Audit | D13: Room Booked Details | E13: Hotel / Reservations | F13: /room_booked_details | G13: Hotel / Reservations, Master Data | H13: 2 | I13: 2 | J13: V/C/E/D | K13: V/C/E | L13: - | M13: - | N13: - | O13: =COUNTIF(J13:N13,"<>-") | P13: Needs deploy
A14: 10 | B14: Submenu | C14: Night Audit | D14: Settlement Summary | E14: Hotel / Reservations | F14: /settlement_summary | G14: Hotel / Reservations, Master Data | H14: 2 | I14: 2 | J14: V/C/E/D | K14: V/C/E | L14: - | M14: - | N14: - | O14: =COUNTIF(J14:N14,"<>-") | P14: Needs deploy
A15: 11 | B15: Menu | C15: - | D15: Guest Enquiry | E15: Hotel / Reservations | F15: /guest_enquiry | G15: Hotel / Reservations, Master Data | H15: 7 | I15: 3 | J15: V/C/E/D | K15: V/C/E | L15: V/C/E | M15: - | N15: - | O15: =COUNTIF(J15:N15,"<>-") | P15: Needs deploy
A16: 12 | B16: Submenu | C16: House Keeper | D16: Task Assign | E16: Hotel / Reservations | F16: /task_assign | G16: HRM / Users, Hotel / Reservations, Master Data | H16: 10 | I16: 3 | J16: V/C/E/D | K16: V | L16: - | M16: V/C/E | N16: - | O16: =COUNTIF(J16:N16,"<>-") | P16: Needs deploy
A17: 13 | B17: Submenu | C17: House Keeper | D17: Room Incident Log | E17: Hotel / Reservations | F17: /room_incident_log | G17: HRM / Users, Hotel / Reservations, Master Data | H17: 10 | I17: 3 | J17: V/C/E/D | K17: V | L17: - | M17: V/C/E | N17: - | O17: =COUNTIF(J17:N17,"<>-") | P17: Needs deploy
A18: 14 | B18: Submenu | C18: HRM | D18: Employee | E18: HRM / Users | F18: /employee | G18: HRM / Users, Master Data | H18: 11 | I18: 1 | J18: V/C/E/D | K18: - | L18: - | M18: - | N18: - | O18: =COUNTIF(J18:N18,"<>-") | P18: Open
A19: 15 | B19: Submenu | C19: HRM | D19: User | E19: HRM / Users | F19: /user | G19: HRM / Users | H19: 3 | I19: 1 | J19: V/C/E/D | K19: - | L19: - | M19: - | N19: - | O19: =COUNTIF(J19:N19,"<>-") | P19: Open | Q19: Only role in the product refused unauthenticated reads (401).
A20: 16 | B20: Submenu | C20: HRM | D20: Roles | E20: HRM / Users | F20: /roles | G20: HRM / Users | H20: 4 | I20: 1 | J20: V/C/E/D | K20: - | L20: - | M20: - | N20: - | O20: =COUNTIF(J20:N20,"<>-") | P20: Open | Q20: QA-DATA-001: 9 test-harness roles are visible on this screen.
A21: 17 | B21: Submenu | C21: HRM | D21: Department | E21: HRM / Users | F21: /department | G21: HRM / Users | H21: 4 | I21: 1 | J21: V/C/E/D | K21: - | L21: - | M21: - | N21: - | O21: =COUNTIF(J21:N21,"<>-") | P21: Open
A22: 18 | B22: Submenu | C22: HRM | D22: Designation | E22: HRM / Users | F22: /designation | G22: HRM / Users | H22: 4 | I22: 1 | J22: V/C/E/D | K22: - | L22: - | M22: - | N22: - | O22: =COUNTIF(J22:N22,"<>-") | P22: Open
A23: 19 | B23: Submenu | C23: HRM | D23: Shift | E23: HRM / Users | F23: /shift | G23: HRM / Users | H23: 4 | I23: 1 | J23: V/C/E/D | K23: - | L23: - | M23: - | N23: - | O23: =COUNTIF(J23:N23,"<>-") | P23: Open
A24: 20 | B24: Submenu | C24: HRM | D24: Restaurant Roster | E24: HRM / Users | F24: /restaurant_roster | G24: HRM / Users, Restaurant (F&B) | H24: 5 | I24: 1 | J24: V/C/E/D | K24: - | L24: - | M24: - | N24: - | O24: =COUNTIF(J24:N24,"<>-") | P24: Open
A25: 21 | B25: Submenu | C25: HRM | D25: Restaurant Shift Planning | E25: HRM / Users | F25: /restaurant_shift_planning | G25: HRM / Users, Restaurant (F&B) | H25: 9 | I25: 1 | J25: V/C/E/D | K25: - | L25: - | M25: - | N25: - | O25: =COUNTIF(J25:N25,"<>-") | P25: Open
A26: 22 | B26: Submenu | C26: HRM | D26: Bar Roster | E26: HRM / Users | F26: /bar_roster | G26: Bar, HRM / Users | H26: 5 | I26: 1 | J26: V/C/E/D | K26: - | L26: - | M26: - | N26: - | O26: =COUNTIF(J26:N26,"<>-") | P26: Open
A27: 23 | B27: Submenu | C27: HRM | D27: Bar Shift Planning | E27: HRM / Users | F27: /bar_shift_planning | G27: Bar, HRM / Users | H27: 9 | I27: 1 | J27: V/C/E/D | K27: - | L27: - | M27: - | N27: - | O27: =COUNTIF(J27:N27,"<>-") | P27: Open
A28: 24 | B28: Submenu | C28: Restaurant | D28: Menu Management | E28: Restaurant (F&B) | F28: /menus | G28: Restaurant (F&B) | H28: 16 | I28: 2 | J28: V/C/E/D | K28: - | L28: - | M28: - | N28: V/C/E | O28: =COUNTIF(J28:N28,"<>-") | P28: Fixed in source
A29: 25 | B29: Submenu | C29: Restaurant | D29: Combo / Package Deals | E29: Restaurant (F&B) | F29: /combo_deals | G29: Restaurant (F&B) | H29: 5 | I29: 2 | J29: V/C/E/D | K29: - | L29: - | M29: - | N29: V/C/E | O29: =COUNTIF(J29:N29,"<>-") | P29: Fixed in source
A30: 26 | B30: Submenu | C30: Restaurant | D30: Floor Layout | E30: Restaurant (F&B) | F30: /floor_layout | G30: Restaurant (F&B) | H30: 4 | I30: 2 | J30: V/C/E/D | K30: - | L30: - | M30: - | N30: V/C/E | O30: =COUNTIF(J30:N30,"<>-") | P30: Fixed in source
A31: 27 | B31: Submenu | C31: Restaurant | D31: Table Master | E31: Restaurant (F&B) | F31: /table_master | G31: Restaurant (F&B) | H31: 5 | I31: 2 | J31: V/C/E/D | K31: - | L31: - | M31: - | N31: V/C/E | O31: =COUNTIF(J31:N31,"<>-") | P31: Fixed in source
A32: 28 | B32: Submenu | C32: Restaurant | D32: Order Management | E32: Restaurant (F&B) | F32: /orders | G32: Restaurant (F&B) | H32: 9 | I32: 2 | J32: V/C/E/D | K32: - | L32: - | M32: - | N32: V/C/E | O32: =COUNTIF(J32:N32,"<>-") | P32: Fixed in source
... A64: 60 | B64: Submenu | C64: Master Data | D64: Reservation Status | E64: Master Data | F64: /reservation_status | G64: Master Data | H64: 4 | I64: 2 | J64: V/C/E/D | K64: V | L64: - | M64: - | N64: - | O64: =COUNTIF(J64:N64,"<>-") | P64: No defect found
A66: TOTALS | D66: =COUNTA(D5:D64) | F66: pages | G66: routes | H66: =SUM(H5:H64)

Sheet Role Access Matrix
A1: Role access, as the database actually grants it
A2: V/A/E/D = view / add / edit / delete. This is the permission data itself, not a re-derivation. Column totals are formulas.
A4: # | B4: Label | C4: Path | D4: Admin | E4: F.O. Manager | F4: Front Desk | G4: Housekeeping | H4: F&B
A5: 1 | B5: Dashboard | C5: /dashboard | D5: V/C/E/D | E5: V | F5: V | G5: V | H5: V
A6: 2 | B6: Reservation | C6: /reservation | D6: V/C/E/D | E6: V/C/E/D | F6: V/C/E | G6: V | H6: -
A7: 3 | B7: Add New Reservation | C7: /add_new_reservation | D7: V/C/E/D | E7: V/C/E/D | F7: V/C/E | G7: V | H7: -
A8: 4 | B8: Booking | C8: /booking | D8: V/C/E/D | E8: V/C/E/D | F8: V/C/E | G8: V | H8: -
A9: 5 | B9: Room View | C9: /room_view | D9: V/C/E/D | E9: V/C/E/D | F9: V/C/E | G9: V | H9: -
A10: 6 | B10: Reservation View | C10: /reservation_view | D10: V/C/E/D | E10: V/C/E/D | F10: V/C/E | G10: V | H10: -
A11: 7 | B11: Night Audit | C11: /night_audit | D11: V/C/E/D | E11: V/C/E | F11: - | G11: - | H11: -
A12: 8 | B12: User Reserved Details | C12: /user_reserved_details | D12: V/C/E/D | E12: V/C/E | F12: - | G12: - | H12: -
A13: 9 | B13: Room Booked Details | C13: /room_booked_details | D13: V/C/E/D | E13: V/C/E | F13: - | G13: - | H13: -
A14: 10 | B14: Settlement Summary | C14: /settlement_summary | D14: V/C/E/D | E14: V/C/E | F14: - | G14: - | H14: -
A15: 11 | B15: Guest Enquiry | C15: /guest_enquiry | D15: V/C/E/D | E15: V/C/E | F15: V/C/E | G15: - | H15: -
A16: 12 | B16: Task Assign | C16: /task_assign | D16: V/C/E/D | E16: V | F16: - | G16: V/C/E | H16: -
... A64: 60 | B64: Reservation Status | C64: /reservation_status | D64: V/C/E/D | E64: V | F64: - | G64: - | H64: -
B66: PAGES GRANTED | D66: =COUNTIF(D5:D64,"<>-") | E66: =COUNTIF(E5:E64,"<>-") | F66: =COUNTIF(F5:F64,"<>-") | G66: =COUNTIF(G5:G64,"<>-") | H66: =COUNTIF(H5:H64,"<>-")

Sheet Findings
A1: Findings - every issue raised by this audit
A2: Severity is the impact if exploited or left in place. Status says what has actually happened to it, not what is planned.
A4: ID | B4: Severity | C4: Finding | D4: Status | E4: Where | F4: Root cause | G4: Fix | H4: Evidence
A5: QA-SEC-001 | B5: Critical | C5: Gateway RBAC runs in `audit`: every role can read and write everything | D5: Fixed in source | E5: LoginServices/resources/rbac.py | F5: MODE defaulted to `audit`, so the 279-row map was computed and discarded. | G5: Default changed to `enforce`; a misspelt value logs CRITICAL and falls forward. | H5: test_rbac_gateway.py 71 + test_route_policy.py 18
A6: QA-SEC-001b | B6: Critical | C6: 179 write route+method pairs had no authorisation layer at all | D6: Needs deploy | E6: All 5 services | F6: Permissions were enforced only at the gateway; the services themselves checked only that a token was valid. | G6: Each service now applies its own slice of the same map, generated by the same run. Ships in `audit` so the deploy changes no behaviour. | H6: 18 exhaustive cross-checks; full suite passes under `enforce` too
A7: QA-SEC-002 | B7: Critical | C7: All five backend services answered on the public IP | D7: Fixed in source | E7: All 5 services main.py | F7: Services were started outside start-network.ps1/run.sh, so nothing read SERVICE_HOST and uvicorn bound 0.0.0.0. | G7: Import-time guard refuses a non-loopback SERVICE_HOST in every env; ALLOW_PUBLIC_BIND=true is the deliberate opt-out. | H7: test_bind_guard.py: 5 services x 7 cases + message check = 42/42
A8: QA-SEC-003 | B8: Critical | C8: JWT expiry appeared not to be enforced | D8: Closed | E8: All 6 services | F8: Not a defect. The deployment's clock is wrong (QA-SEC-009), and the token was compared against the reviewer's clock. | G8: No source change needed - the deployment now refuses an expired token on all six surfaces. Added preflight checks 3b/3c so it cannot regress. | H8: expiry_recheck.py: 401 expired / 200 fresh / 401 mangled, x6 surfaces
A9: QA-SEC-009 | B9: Critical | C9: The deployment's clock is 13.4 hours behind | D9: Open | E9: Deployment host (configuration) | F9: No time sync on the host. Everything the system records is stamped from it: JWT iat/exp, night audit business_date, arrival comparisons, payments. | G9: NTP on the host. Not a source fix - but preflight check 3b now fails whenever the clocks disagree, so it cannot regress unnoticed. | H9: clock_and_expiry.py: server Date header vs local, 48209s
A10: QA-SEC-004 | B10: Critical | C10: All six services run with development configuration | D10: Open | E10: Deployment configuration | F10: ASCEND_ENV is not `production`, so /docs, /redoc and /openapi.json are public. No TLS either. | G10: Set ASCEND_ENV=production and terminate TLS in front of the gateway. verify_prod_env.py already fails this host on ASCEND_ENV alone. | H10: preflight.py check 1-6
A11: QA-BIZ-001 | B11: High | C11: A cancellation could be re-recorded, destroying the reason | D11: Fixed in source | E11: HotelServices reservationController.py | F11: cancel_reservation had no terminal guard, so a second call overwrote the first call's reason with a default. | G11: 409 when the current state already forbids cancelling. Uses rules.can_offer, the same expression the UI's can_cancel uses, so the button and the endpoint cannot disagree. | H11: test_reservation_rules.py 111 assertions
A12: QA-BIZ-002 | B12: High | C12: A guest could be quoted a price for a room that cannot be booked | D12: Fixed in source | E12: HotelServices reservation_rules.py | F12: The quote path validated dates and tenant scope but not that the rooms were sellable - blocked, out of order or housekeeping-held. | G12: Extracted assert_rooms_sellable() and wired it into the quote endpoint. | H12: test_reservation_rules.py 111 assertions
A13: QA-SEC-005 | B13: High | C13: Guest phone and email reachable from the one page every role holds | D13: Fixed in source | E13: HotelDashboardTab.jsx + rbac_map.py | F13: The dashboard called /hotel/user_activity_log, whose map row granted /dashboard - a page all five roles hold. | G13: The dashboard card is sourced from reservation_summary + housekeeper_tasks instead; the map row was regenerated, not hand-edited. | H13: test_rbac_gateway.py 71; map diff is exactly 1 row
A14: QA-SEC-006 | B14: Medium | C14: Housekeeping holds read on the whole reservation book | D14: Owner decision | E14: role_permissions seed | F14: The Housekeeping role is granted view on reservation screens, which shows guest names, phones and emails to a role that does not need them. | G14: A grant to remove. Needs the business to say what Housekeeping actually needs - which is why it is not changed unilaterally. | H14: privesc_matrix.py: 8 pages, of which 3 are reservation
A15: QA-SEC-007 | B15: Medium | C15: SPA answers `200 text/html` for every unknown path, including images | D15: Fixed in source | E15: Frontend/serve-spa.mjs (new) | F15: The history fallback was unconditional, so a missing asset returned 200 HTML and could not be distinguished from a working one. | G15: Fallback now applies only to a client-side route: no extension, and Accept: text/html. Missing assets are a true 404. | H15: test_spa_fallback.py: 21 checks, counted from the script's [PASS] lines
... A20: QA-UX-001 | B20: Withdrawn | C20: Reported earlier, then withdrawn | D20: Closed | E20: QA measurement | F20: My own measurement error: innerText is empty for the image-only loader, so the 'empty loader' reading was an artefact of how it was measured. | G20: Withdrawn. No source change was made for it. | H20: n/a - never a defect
A22: Critical | B22: =COUNTIF($B$5:$B$20,A22) | C22: =IF(B22=0,"none","")
A23: High | B23: =COUNTIF($B$5:$B$20,A23) | C23: =IF(B23=0,"none","")
A24: Medium | B24: =COUNTIF($B$5:$B$20,A24) | C24: =IF(B24=0,"none","")
A25: Low | B25: =COUNTIF($B$5:$B$20,A25) | C25: =IF(B25=0,"none","")
A26: Withdrawn | B26: =COUNTIF($B$5:$B$20,A26) | C26: =IF(B26=0,"none","")

Sheet Pending & Blocked
A1: What is still open, and what it needs
A2: 'Blocks production' is the honest question: an item marked YES means the deployment is not production-ready without it.
A4: # | B4: Item | C4: Why it is still open | D4: Owner | E4: Blocks production? | F4: Exact action
A5: 1 | B5: QA-SEC-009 Fix the host clock (NTP) | C5: Host configuration, not code | D5: Infrastructure | E5: YES | F5: Enable NTP, then: python Backend/tools/preflight.py --host <server> - check 3b must pass
A6: 2 | B6: QA-SEC-004 ASCEND_ENV=production + TLS | C6: Deployment configuration | D6: Infrastructure | E6: YES | F6: Set ASCEND_ENV=production in each service .env; terminate TLS in front of :9010
A7: 3 | B7: QA-SEC-001b Flip the service guard to enforce | C7: Ships in audit on purpose: a third control changing at once with two others is how a deploy day goes wrong | D7: Release owner | E7: No | F7: grep rbac_would_deny .run-logs/*.log | head -50, then set ROUTE_POLICY_MODE=enforce
A8: 4 | B8: QA-SEC-008 Rotate the demo password | C8: Redaction removed the published copy; it does not un-publish the one already in every clone | D8: Release owner | E8: YES | F8: python Backend/tools/rotate_passwords.py --confirm --out <file>. preflight check 5 fails until this is done.
A9: 5 | B9: QA-SEC-008 Purge the password from git history | C9: Needs a history rewrite and a force-push, which invalidates every clone | D9: Repo owner | E9: No | F9: git filter-repo --replace-text, then force-push and tell everyone
A10: 6 | B10: QA-SEC-006 Housekeeping reservation grants | C10: A business decision: what Housekeeping actually needs is not derivable from the code | D10: Product owner | E10: No | F10: Decide, then amend role_permissions for role 4
A11: 7 | B11: QA-DATA-001 Remove the 9 test roles | C11: Data hygiene in the committed dump | D11: Release owner | E11: No | F11: Delete roles 6-14 from hotelerp_users.sql and re-export
A12: 8 | B12: npm run build Cannot run on the QA machine | C12: @oxc-resolver's win32 binding fails ERR_DLOPEN_FAILED here. Environment, not code. | D12: Whoever deploys | E12: YES | F12: Run the build on the deploy host or CI, then serve with node Frontend/serve-spa.mjs
A13: 9 | B13: Owner decision: should QA runbooks be in the repo? | C13: QA/live/ holds re-runnable harness scripts that invite someone to re-run them against a live host | D13: Repo owner | E13: No | F13: Decide: keep them in-repo, or move to a private location
B15: ITEMS BLOCKING PRODUCTION READINESS | E15: =COUNTIF(E5:E13,"YES")

Sheet Go-Live Flow
A1: Go-live sequence - in order, with the check at each step
A2: Steps 1-7 are deployment work. Step 8 is the gate: if preflight fails, stop. Step 11 is what turns this audit's unit-test proof into live proof.
A4: Step | B4: Action | C4: Why it is in this order | D4: Command / check | E4: Owner
A5: 1 | B5: Commit and deploy HEAD | C5: 36 modified files, 14 new. Nothing is committed yet. | D5: git add -A && git commit -m 'QA fixes' && deploy | E5: Deploy owner
A6: 2 | B6: Bind the services to loopback | C6: The launcher already does this; make sure nothing else is what started them. | D6: start-network.ps1, or run.sh. ALLOW_PUBLIC_BIND must NOT be set. | E6: Deploy owner
A7: 3 | B7: Fix the host clock first | C7: A 13.4h skew makes every timestamp wrong and every session look expired. | D7: Enable NTP, then confirm with preflight check 3b | E7: Infrastructure
A8: 4 | B8: Set ASCEND_ENV=production in every service .env | C8: Turns off /docs, /redoc and /openapi.json. | D8: verify_prod_env.py will refuse to start otherwise | E8: Deploy owner
A9: 5 | B9: Rotate the demo password | C9: It is in git history and in every clone. | D9: rotate_passwords.py --confirm --out <file> | E9: Release owner
A10: 6 | B10: Build the frontend | C10: Could not be built on the QA machine. | D10: npm run build, then serve dist with node Frontend/serve-spa.mjs | E10: Deploy owner
A11: 7 | B11: Terminate TLS in front of the gateway | C11: Credentials and session tokens currently cross the wire in clear. | D11: Reverse proxy on :443 -> :9010 | E11: Infrastructure
A12: 8 | B12: Run preflight against the new deployment | C12: The gate. Six checks, and it now also checks token lifetime. | D12: python Backend/tools/preflight.py --host <server> | E12: Deploy owner
A13: 9 | B13: Read the service guard's audit log | C13: This is what turns the audit log from theory into evidence for THIS data. | D13: grep rbac_would_deny .run-logs/*.log | head -50 | E13: Release owner
A14: 10 | B14: Flip ROUTE_POLICY_MODE=enforce and restart | C14: Only safe once step 9 is clean. | D14: ROUTE_POLICY_MODE=enforce in each service .env | E14: Release owner
A15: 11 | B15: Re-run the QA sweep against the new deployment | C15: The fixes are verified by unit tests and map regeneration; only a live request proves them end to end. | D15: QA/live/sweep_api.py, privesc_matrix.py, workflow_checks.py | E15: QA
A16: 12 | B16: Sign off | C16: Everything above green. | D16: Update the Module Status tab in this workbook | E16: Release owner

Sheet Test Evidence
A1: Regression evidence - every suite, straight from the run
A2: Read from QA/live/regression_run.json, which is parsed from the output of python Backend/tests/run_all.py. A pytest suite and a script suite count differently, so they are shown separately.
A4: Suite | B4: Runs from | C4: Kind | D4: Checks | E4: What it protects | F4: Result
A5: test_rbac.py | B5: UserServices | C5: pytest | D5: 19 | E5: Permission decisions inside the user service | F5: Pass
A6: test_rbac_gateway.py | B6: LoginServices | C6: pytest | D6: 71 | E6: The gateway's 279-row permission map | F6: Pass
A7: test_route_policy.py | B7: LoginServices | C7: pytest | D7: 18 | E7: Service guard agrees with the gateway, all 279 routes | F7: Pass
A8: test_night_audit.py | B8: HotelServices | C8: pytest | D8: 50 | E8: Business date, postings, reconciliation | F8: Pass
A9: test_reservation_rules.py | B9: HotelServices | C9: pytest | D9: 111 | E9: Cancellation, pricing, sellability, folio rules | F9: Pass
A10: test_reservation_pricing.py | B10: HotelServices | C10: pytest | D10: 10 | E10: Folio arithmetic over the real HTTP client | F10: Pass
A11: test_booking_validation.py | B11: HotelServices | C11: pytest | D11: 24 | E11: Dates, numeric bounds, room-type scope | F11: Pass
A12: test_reservation_housekeeping.py | B12: HotelServices | C12: pytest | D12: 23 | E12: Checkout -> housekeeping handover on the wire | F12: Pass
A13: test_preflight_images.py | B13: LoginServices | C13: pytest | D13: 7 | E13: Preflight check 6: are the images really on disk | F13: Pass
A14: test_seed_night_audit.py | B14: LoginServices | C14: pytest | D14: 10 | E14: Seeded audit rows reconcile with seeded bookings | F14: Pass
A15: test_master_client.py | B15: HotelServices | C15: pytest | D15: 45 | E15: The service-to-service HTTP client and its failure modes | F15: Pass
A16: test_snapshot_contract.py | B16: MasterDataServices | C16: pytest | D16: 12 | E16: /snapshot contract, asserted from both ends | F16: Pass
... A41: remove_frozen_dates.py | B41: repo root | C41: script | D41: 6 | E41: Invariant: no import-time date constant remains | F41: Pass
A43: TOTALS | B43: =COUNTA(A5:A41)&' suites' | C43: =COUNTIF(C5:C41,"pytest")&'+'&COUNTIF(C5:C41,"script") | D43: =SUM(D5:D41) | E43: =SUMPRODUCT((C5:C41="pytest")*D5:D41)&" pytest assertions + "&SUMPRODUCT((C5:C41="script")*D5:D41)&" script checks. Identical under ROUTE_POLICY_MODE=audit and enforce." | F43: =COUNTIF(F5:F41,"FAIL")&" failed"
